oven_mlir-0.1.1.data/purelib/oven_mlir/CMakeLists.txt
oven_mlir-0.1.1.data/purelib/oven_mlir/__init__.py
oven_mlir-0.1.1.data/purelib/oven_mlir/cli.py
oven_mlir-0.1.1.data/purelib/oven_mlir/oven.py
oven_mlir-0.1.1.data/purelib/oven_mlir/oven_opt_bindings.cpp
oven_mlir-0.1.1.data/purelib/oven_mlir/oven_opt_py.cpython-310-x86_64-linux-gnu.so
oven_mlir-0.1.1.data/purelib/oven_mlir/python_to_ptx.py
oven_mlir-0.1.1.dist-info/licenses/LICENSE
oven_mlir-0.1.1.dist-info/METADATA
oven_mlir-0.1.1.dist-info/WHEEL
oven_mlir-0.1.1.dist-info/entry_points.txt
oven_mlir-0.1.1.dist-info/top_level.txt
oven_mlir-0.1.1.dist-info/RECORD
